lintify/__init__.py
lintify/cli.py
lintify/compat.py
lintify/config.yaml
lintify/frames.py
lintify/fs.py
lintify/linters.py
lintify/load_conf.py
lintify/main.py
lintify/old.py
lintify/output.py
lintify/renderers.py
lintify/schemas.py
lintify/utils.py
lintify-0.1.0.dist-info/METADATA
lintify-0.1.0.dist-info/WHEEL
lintify-0.1.0.dist-info/entry_points.txt
lintify-0.1.0.dist-info/RECORD
