Metadata-Version: 2.1
Name: lintify
Version: 0.1.0
Summary: 
Author: Titov Anton
Author-email: webdev@titovanton.com
Requires-Python: >=3.10,<4.0
Classifier: Programming Language :: Python :: 3
Classifier: Programming Language :: Python :: 3.10
Classifier: Programming Language :: Python :: 3.11
Requires-Dist: click (>=8.1.7,<9.0.0)
Requires-Dist: pydantic (>=2.8.2,<3.0.0)
Requires-Dist: pyyaml (>=6.0.2,<7.0.0)
Requires-Dist: types-pyyaml (>=6.0.12.20240808,<7.0.0.0)
Requires-Dist: watchdog (>=4.0.1,<5.0.0)
